{
  "os":  "Linux-5.14.0-427.76.1.el9_4.x86_64-x86_64-with-glibc2.34",
  "python":  "CPython 3.10.19",
  "startedAt":  "2025-11-11T02:20:31.778114Z",
  "args":  [
    "task=bin",
    "model=llama32",
    "train=dpo",
    "cluster=osc_ascend",
    "seed=0",
    "prefix=my_experiment",
    "gpu_nums=0",
    "wandb=1",
    "project=evotune-reproducing",
    "entity=hananenmoussa"
  ],
  "program":  "/fs/ess/PAA0201/hananemoussa/EvoTune/src/experiments/main.py",
  "codePath":  "src/experiments/main.py",
  "codePathLocal":  "src/experiments/main.py",
  "git":  {
    "remote":  "https://github.com/hananemoussa/EvoTune.git",
    "commit":  "9c55ee21a4459e8601bf9b7d61ef2cc9871d6012"
  },
  "root":  "/fs/ess/PAA0201/hananemoussa/EvoTune",
  "host":  "a0014.ten.osc.edu",
  "executable":  "/users/PAA0201/hananemoussa/.conda/envs/evotune/bin/python",
  "cpu_count":  96,
  "cpu_count_logical":  96,
  "gpu":  "NVIDIA A100-SXM4-80GB",
  "gpu_count":  1,
  "disk":  {
    "/":  {
      "total":  "204010946560",
      "used":  "32968343552"
    }
  },
  "memory":  {
    "total":  "1081776664576"
  },
  "gpu_nvidia":  [
    {
      "name":  "NVIDIA A100-SXM4-80GB",
      "memoryTotal":  "85899345920",
      "cudaCores":  6912,
      "architecture":  "Ampere",
      "uuid":  "GPU-025dd8c5-db98-0607-090d-e9ceb0de82ae"
    }
  ],
  "cudaVersion":  "12.4",
  "slurm":  {
    "cluster_name":  "ascend",
    "conf":  "/var/spool/slurmd/conf-cache/slurm.conf",
    "cpus_on_node":  "1",
    "cpus_per_task":  "1",
    "distribution":  "pack",
    "gpus":  "1",
    "gpus_on_node":  "1",
    "gtids":  "0",
    "job_account":  "paa0201",
    "job_cpus_per_node":  "1",
    "job_end_time":  "1762834653",
    "job_gid":  "6044",
    "job_gpus":  "2",
    "job_id":  "2837454",
    "job_name":  "interactive",
    "job_nodelist":  "a0014",
    "job_num_nodes":  "1",
    "job_partition":  "quad",
    "job_qos":  "ascend-default",
    "job_start_time":  "1762820253",
    "job_uid":  "46117",
    "job_user":  "hananemoussa",
    "jobid":  "2837454",
    "launch_node_ipaddr":  "192.148.247.181",
    "localid":  "0",
    "mpi_type":  "pmi2",
    "nnodes":  "1",
    "nodeid":  "0",
    "nodelist":  "a0014",
    "nprocs":  "1",
    "ntasks":  "1",
    "pmi2_proc_mapping":  "(vector,(0,1,1))",
    "pmi2_srun_port":  "39203",
    "pmi2_step_nodes":  "a0014",
    "prio_process":  "0",
    "procid":  "0",
    "pty_port":  "34111",
    "pty_win_col":  "152",
    "pty_win_row":  "37",
    "script_context":  "prolog_task",
    "srun_comm_host":  "192.148.247.181",
    "srun_comm_port":  "38715",
    "step_id":  "4294967290",
    "step_launcher_port":  "38715",
    "step_nodelist":  "a0014",
    "step_num_nodes":  "1",
    "step_num_tasks":  "1",
    "step_tasks_per_node":  "1",
    "stepid":  "4294967290",
    "submit_dir":  "/fs/ess/PAA0201/hananemoussa",
    "submit_host":  "ascend-login02.hpc.osc.edu",
    "task_pid":  "2492849",
    "tasks_per_node":  "1",
    "time_limit":  "14400",
    "topology_addr":  "a0014",
    "topology_addr_pattern":  "node",
    "tres_per_task":  "cpu=1"
  },
  "writerId":  "3khs5n1irjgbrm31tss70mt9pd3tj4yk"
}